{"country":"LIE","year":2000,"n_students":176,"data_quality":{"missing_math":104,"missing_reading":0,"missing_science":0,"missing_escs":1,"complete_cases":71},"students":[{"year":2000,"country":"LIE","school_id":"LIE_2000_51003","student_id":"LIE_2000_1","gender":"male","internet":"yes","science":451.68,"stu_wgt":1.8783,"desk":"yes","room":"yes","dishwasher":"yes","television":"2","computer_n":"2","car":"3+","book":"51-100","wealth":1.46,"escs":0.505,"reading":426.58},{"year":2000,"country":"LIE","school_id":"LIE_2000_51003","student_id":"LIE_2000_2","gender":"female","internet":"no","science":391.08,"stu_wgt":1.8783,"desk":"yes","room":"yes","dishwasher":"yes","television":"2","computer_n":"0","book":"11-50","wealth":-1.17,"escs":-1.4712,"reading":438.69},{"year":2000,"country":"LIE","school_id":"LIE_2000_51003","student_id":"LIE_2000_6","gender":"male","internet":"no","science":475.13,"stu_wgt":1.8783,"desk":"yes","room":"yes","dishwasher":"no","television":"1","computer_n":"0","car":"1","book":"more than 500","wealth":-1.46,"escs":0.7066,"reading":467.48},{"year":2000,"country":"LIE","school_id":"LIE_2000_51003","student_id":"LIE_2000_8","gender":"male","internet":"yes","science":520.04,"stu_wgt":1.8783,"desk":"yes","room":"yes","dishwasher":"yes","television":"3+","computer_n":"1","car":"2","book":"101-250","wealth":0.85,"escs":-0.5474,"reading":508.04},{"year":2000,"country":"LIE","school_id":"LIE_2000_51003","student_id":"LIE_2000_12","gender":"male","internet":"yes","science":577.77,"stu_wgt":1.8783,"desk":"yes","room":"yes","dishwasher":"yes","television":"2","computer_n":"2","car":"2","book":"101-250","wealth":0.85,"escs":-0.3697,"reading":584.39},{"year":2000,"country":"LIE","school_id":"LIE_2000_51003","student_id":"LIE_2000_13","gender":"female","internet":"yes","math":538.79,"science":542.25,"stu_wgt":1.8783,"desk":"yes","room":"yes","dishwasher":"yes","television":"3+","computer_n":"2","car":"3+","book":"1-10","wealth":1.84,"escs":0.7757,"reading":577.79},{"year":2000,"country":"LIE","school_id":"LIE_2000_51003","student_id":"LIE_2000_14","gender":"male","internet":"no","science":387.47,"stu_wgt":1.8783,"desk":"yes","room":"yes","dishwasher":"yes","television":"3+","computer_n":"0","car":"3+","book":"1-10","wealth":0.11,"escs":-0.9896,"reading":407.79},{"year":2000,"country":"LIE","school_id":"LIE_2000_51003","student_id":"LIE_2000_16","gender":"female","internet":"yes","math":444.15,"science":480.01,"stu_wgt":1.8783,"desk":"yes","room":"yes","dishwasher":"yes","television":"2","computer_n":"1","car":"2","book":"11-50","wealth":0.85,"escs":-0.1209,"reading":457.81},{"year":2000,"country":"LIE","school_id":"LIE_2000_51003","student_id":"LIE_2000_17","gender":"female","internet":"yes","science":463.25,"stu_wgt":1.8783,"desk":"yes","room":"yes","dishwasher":"yes","television":"2","computer_n":"3+","car":"3+","book":"251-500","wealth":1.84,"escs":1.5711,"reading":505.95},{"year":2000,"country":"LIE","school_id":"LIE_2000_51003","student_id":"LIE_2000_18","gender":"male","internet":"yes","math":606.75,"science":529.69,"stu_wgt":1.8783,"desk":"yes","room":"yes","dishwasher":"yes","television":"2","computer_n":"1","car":"2","book":"51-100","wealth":0.34,"escs":-0.4247,"reading":582.39},{"year":2000,"country":"LIE","school_id":"LIE_2000_51003","student_id":"LIE_2000_19","gender":"male","internet":"yes","science":510.12,"stu_wgt":1.8783,"desk":"yes","room":"yes","dishwasher":"yes","television":"2","computer_n":"1","car":"1","book":"101-250","wealth":-0.12,"escs":0.1507,"reading":528.94},{"year":2000,"country":"LIE","school_id":"LIE_2000_51003","student_id":"LIE_2000_22","gender":"female","internet":"yes","science":457.99,"stu_wgt":1.8783,"desk":"no","room":"yes","dishwasher":"yes","television":"1","computer_n":"0","car":"2","book":"11-50","wealth":-0.12,"escs":0.5895,"reading":443.85},{"year":2000,"country":"LIE","school_id":"LIE_2000_51004","student_id":"LIE_2000_26","gender":"male","internet":"no","math":522.76,"science":479.1,"stu_wgt":2.0572,"desk":"yes","room":"yes","dishwasher":"yes","television":"1","computer_n":"1","car":"2","book":"11-50","wealth":-0.36,"escs":-0.7457,"reading":497.81},{"year":2000,"country":"LIE","school_id":"LIE_2000_51004","student_id":"LIE_2000_29","gender":"male","internet":"yes","science":591.34,"stu_wgt":2.0572,"desk":"yes","room":"yes","dishwasher":"yes","television":"2","computer_n":"2","car":"1","book":"11-50","wealth":-0.36,"escs":0.4498,"reading":533.22},{"year":2000,"country":"LIE","school_id":"LIE_2000_51004","student_id":"LIE_2000_31","gender":"female","internet":"yes","science":396.5,"stu_wgt":2.0572,"desk":"yes","room":"yes","dishwasher":"yes","television":"2","computer_n":"0","car":"1","book":"101-250","wealth":-0.6,"escs":-0.5002,"reading":415.06},{"year":2000,"country":"LIE","school_id":"LIE_2000_51004","student_id":"LIE_2000_32","gender":"female","internet":"no","math":406.78,"science":418.73,"stu_wgt":2.0572,"desk":"yes","room":"yes","dishwasher":"yes","television":"2","computer_n":"2","car":"1","book":"11-50","wealth":-0.12,"escs":-0.604,"reading":478.77},{"year":2000,"country":"LIE","school_id":"LIE_2000_51004","student_id":"LIE_2000_35","gender":"female","internet":"no","science":430.03,"stu_wgt":2.0572,"desk":"yes","room":"yes","dishwasher":"yes","television":"1","computer_n":"1","car":"2","book":"11-50","wealth":0.11,"escs":-0.3035,"reading":474.75},{"year":2000,"country":"LIE","school_id":"LIE_2000_51004","student_id":"LIE_2000_37","gender":"female","internet":"no","math":515.13,"science":483.61,"stu_wgt":2.0572,"desk":"yes","room":"yes","dishwasher":"no","television":"3+","computer_n":"0","car":"3+","book":"251-500","wealth":0.59,"escs":0.1335,"reading":542.34},{"year":2000,"country":"LIE","school_id":"LIE_2000_51004","student_id":"LIE_2000_38","gender":"male","internet":"no","science":499.49,"stu_wgt":2.0572,"desk":"yes","room":"yes","dishwasher":"yes","television":"1","computer_n":"2","car":"3+","book":"11-50","wealth":0.11,"escs":-0.5535,"reading":458.39},{"year":2000,"country":"LIE","school_id":"LIE_2000_51004","student_id":"LIE_2000_39","gender":"male","internet":"no","math":515.92,"science":493.6,"stu_wgt":2.0572,"desk":"yes","room":"yes","dishwasher":"no","television":"3+","computer_n":"3+","car":"3+","book":"51-100","wealth":0.59,"escs":-1.1793,"reading":493.31},{"year":2000,"country":"LIE","school_id":"LIE_2000_51004","student_id":"LIE_2000_41","gender":"female","internet":"yes","science":502.9,"stu_wgt":2.0572,"desk":"yes","room":"yes","dishwasher":"yes","television":"1","computer_n":"2","car":"1","book":"251-500","wealth":0.11,"escs":0.8436,"reading":535.3},{"year":2000,"country":"LIE","school_id":"LIE_2000_51004","student_id":"LIE_2000_43","gender":"male","internet":"yes","math":572.4,"science":572.99,"stu_wgt":2.0572,"desk":"yes","room":"yes","dishwasher":"yes","television":"3+","computer_n":"3+","car":"2","book":"101-250","wealth":1.84,"escs":1.188,"reading":531.49},{"year":2000,"country":"LIE","school_id":"LIE_2000_51005","student_id":"LIE_2000_45","gender":"female","internet":"no","science":404.77,"stu_wgt":1.8,"desk":"yes","room":"yes","dishwasher":"no","television":"1","computer_n":"1","car":"3+","book":"51-100","wealth":-0.36,"escs":-1.4266,"reading":449.3},{"year":2000,"country":"LIE","school_id":"LIE_2000_51005","student_id":"LIE_2000_46","gender":"female","internet":"no","science":426.23,"stu_wgt":1.8,"desk":"yes","room":"yes","dishwasher":"yes","television":"3+","computer_n":"1","car":"2","book":"11-50","wealth":-0.12,"escs":-0.5594,"reading":433.5},{"year":2000,"country":"LIE","school_id":"LIE_2000_51005","student_id":"LIE_2000_47","gender":"male","internet":"no","science":420.81,"stu_wgt":1.8,"desk":"yes","room":"yes","dishwasher":"no","television":"2","computer_n":"1","car":"1","book":"none","wealth":-0.36,"escs":-0.7764,"reading":397.15},{"year":2000,"country":"LIE","school_id":"LIE_2000_51005","student_id":"LIE_2000_54","gender":"male","internet":"no","science":433.48,"stu_wgt":1.8,"desk":"yes","room":"yes","dishwasher":"yes","television":"1","computer_n":"1","car":"1","book":"1-10","wealth":-0.36,"escs":-1.4817,"reading":316.89},{"year":2000,"country":"LIE","school_id":"LIE_2000_51005","student_id":"LIE_2000_55","gender":"male","internet":"yes","math":336.53,"science":341.99,"stu_wgt":1.8,"desk":"yes","room":"yes","dishwasher":"yes","television":"2","computer_n":"1","car":"2","book":"51-100","wealth":0.85,"escs":-0.7022,"reading":263.3},{"year":2000,"country":"LIE","school_id":"LIE_2000_51005","student_id":"LIE_2000_58","gender":"male","internet":"no","math":474.71,"science":451.21,"stu_wgt":1.8,"desk":"yes","room":"yes","dishwasher":"yes","television":"2","computer_n":"0","car":"2","book":"101-250","wealth":-0.6,"escs":-0.2208,"reading":412.41},{"year":2000,"country":"LIE","school_id":"LIE_2000_51005","student_id":"LIE_2000_60","gender":"male","internet":"no","science":333.51,"stu_wgt":1.8,"desk":"yes","room":"yes","dishwasher":"yes","television":"1","computer_n":"1","car":"1","book":"51-100","wealth":-0.6,"escs":0.0895,"reading":321.14},{"year":2000,"country":"LIE","school_id":"LIE_2000_51005","student_id":"LIE_2000_61","gender":"male","internet":"no","science":380.26,"stu_wgt":1.8,"desk":"yes","room":"yes","dishwasher":"yes","television":"3+","computer_n":"1","car":"2","book":"1-10","wealth":0.11,"escs":-0.4877,"reading":383.24},{"year":2000,"country":"LIE","school_id":"LIE_2000_51005","student_id":"LIE_2000_62","gender":"male","internet":"no","math":373.2,"science":414.22,"stu_wgt":1.8,"desk":"yes","room":"yes","dishwasher":"no","television":"3+","computer_n":"1","car":"2","book":"51-100","wealth":0.59,"escs":-0.9311,"reading":337.88},{"year":2000,"country":"LIE","school_id":"LIE_2000_51005","student_id":"LIE_2000_63","gender":"female","internet":"no","science":447.87,"stu_wgt":1.8,"desk":"yes","room":"no","dishwasher":"yes","television":"2","computer_n":"2","car":"2","book":"101-250","wealth":-0.12,"escs":-0.4116,"reading":472.59},{"year":2000,"country":"LIE","school_id":"LIE_2000_51005","student_id":"LIE_2000_64","gender":"female","internet":"no","math":454.07,"science":505.26,"stu_wgt":1.8,"desk":"yes","room":"yes","dishwasher":"yes","television":"2","computer_n":"3+","car":"2","book":"251-500","wealth":0.11,"escs":-0.8114,"reading":535.98},{"year":2000,"country":"LIE","school_id":"LIE_2000_51005","student_id":"LIE_2000_66","gender":"female","internet":"no","math":497.57,"science":509.77,"stu_wgt":1.8,"desk":"yes","room":"yes","dishwasher":"yes","television":"2","computer_n":"0","car":"1","book":"51-100","wealth":-0.6,"escs":-0.6004,"reading":499.62},{"year":2000,"country":"LIE","school_id":"LIE_2000_51005","student_id":"LIE_2000_67","gender":"male","internet":"no","science":394.69,"stu_wgt":1.8,"desk":"yes","room":"no","dishwasher":"no","television":"2","computer_n":"1","car":"0","book":"101-250","wealth":-0.85,"escs":-1.5001,"reading":424.15},{"year":2000,"country":"LIE","school_id":"LIE_2000_51005","student_id":"LIE_2000_68","gender":"male","internet":"no","math":492.26,"science":379.94,"stu_wgt":1.8,"desk":"yes","room":"yes","dishwasher":"yes","television":"3+","computer_n":"1","car":"2","book":"101-250","wealth":0.34,"escs":0.7491,"reading":369.69},{"year":2000,"country":"LIE","school_id":"LIE_2000_51006","student_id":"LIE_2000_72","gender":"female","internet":"yes","math":694.52,"science":695.67,"stu_wgt":1.8277,"desk":"yes","room":"yes","dishwasher":"yes","television":"1","computer_n":"1","car":"2","book":"more than 500","wealth":-0.36,"escs":1.1666,"reading":705.09},{"year":2000,"country":"LIE","school_id":"LIE_2000_51006","student_id":"LIE_2000_73","gender":"male","internet":"yes","math":656.36,"science":595.54,"stu_wgt":1.8277,"desk":"yes","room":"yes","dishwasher":"yes","television":"2","computer_n":"2","car":"2","book":"1-10","wealth":0.34,"escs":-0.1425,"reading":539.67},{"year":2000,"country":"LIE","school_id":"LIE_2000_51006","student_id":"LIE_2000_74","gender":"female","internet":"yes","math":558.63,"science":556.68,"stu_wgt":1.8277,"desk":"yes","room":"yes","dishwasher":"yes","television":"3+","computer_n":"1","car":"2","book":"101-250","wealth":1.14,"escs":1.5609,"reading":604.15},{"year":2000,"country":"LIE","school_id":"LIE_2000_51006","student_id":"LIE_2000_77","gender":"male","internet":"yes","science":609.54,"stu_wgt":1.8277,"desk":"yes","room":"yes","dishwasher":"yes","television":"1","computer_n":"2","car":"2","book":"more than 500","wealth":0.59,"escs":1.5637,"reading":574.74},{"year":2000,"country":"LIE","school_id":"LIE_2000_51006","student_id":"LIE_2000_78","gender":"male","internet":"yes","math":560.92,"science":520.6,"stu_wgt":1.8277,"desk":"yes","room":"yes","dishwasher":"yes","television":"3+","computer_n":"3+","car":"1","book":"11-50","wealth":1.14,"escs":0.3085,"reading":517.8},{"year":2000,"country":"LIE","school_id":"LIE_2000_51006","student_id":"LIE_2000_79","gender":"male","internet":"yes","science":562.44,"stu_wgt":1.8277,"desk":"yes","room":"yes","dishwasher":"yes","television":"1","computer_n":"2","car":"2","book":"251-500","wealth":0.34,"escs":0.6916,"reading":633.47},{"year":2000,"country":"LIE","school_id":"LIE_2000_51006","student_id":"LIE_2000_82","gender":"male","internet":"no","science":587.7,"stu_wgt":1.8277,"desk":"yes","room":"yes","dishwasher":"no","television":"1","computer_n":"1","car":"1","book":"11-50","wealth":-0.85,"escs":-1.1229,"reading":629.83},{"year":2000,"country":"LIE","school_id":"LIE_2000_51006","student_id":"LIE_2000_84","gender":"female","internet":"no","science":586.99,"stu_wgt":1.8277,"desk":"yes","room":"yes","dishwasher":"yes","television":"2","computer_n":"1","car":"1","book":"51-100","wealth":-0.36,"escs":-0.106,"reading":600.19},{"year":2000,"country":"LIE","school_id":"LIE_2000_51006","student_id":"LIE_2000_85","gender":"female","internet":"yes","science":566.24,"stu_wgt":1.8277,"desk":"yes","room":"yes","dishwasher":"yes","television":"3+","computer_n":"1","car":"2","book":"251-500","wealth":1.46,"escs":1.4645,"reading":583.82},{"year":2000,"country":"LIE","school_id":"LIE_2000_51006","student_id":"LIE_2000_86","gender":"female","internet":"yes","math":645.67,"science":540.51,"stu_wgt":1.8277,"desk":"yes","room":"yes","dishwasher":"yes","television":"3+","computer_n":"2","car":"2","book":"251-500","wealth":0.59,"escs":0.3085,"reading":568.75},{"year":2000,"country":"LIE","school_id":"LIE_2000_51006","student_id":"LIE_2000_87","gender":"female","internet":"yes","science":601.42,"stu_wgt":1.8277,"desk":"yes","room":"yes","dishwasher":"yes","television":"3+","computer_n":"3+","car":"3+","book":"51-100","wealth":2.36,"escs":1.8148,"reading":541.1},{"year":2000,"country":"LIE","school_id":"LIE_2000_51006","student_id":"LIE_2000_89","gender":"male","internet":"yes","science":511.92,"stu_wgt":1.8277,"desk":"yes","room":"yes","dishwasher":"yes","television":"2","computer_n":"2","car":"2","book":"251-500","wealth":0.85,"escs":1.3505,"reading":503.49},{"year":2000,"country":"LIE","school_id":"LIE_2000_51006","student_id":"LIE_2000_91","gender":"male","internet":"yes","science":623.97,"stu_wgt":1.8277,"desk":"yes","room":"yes","dishwasher":"yes","television":"1","computer_n":"2","car":"2","book":"101-250","wealth":0.11,"escs":0.7402,"reading":612},{"year":2000,"country":"LIE","school_id":"LIE_2000_51006","student_id":"LIE_2000_93","gender":"male","internet":"yes","math":598.32,"science":562.09,"stu_wgt":1.8277,"desk":"yes","room":"yes","dishwasher":"yes","television":"2","computer_n":"2","car":"2","book":"251-500","wealth":0.59,"escs":1.2972,"reading":515.08},{"year":2000,"country":"LIE","school_id":"LIE_2000_51006","student_id":"LIE_2000_94","gender":"male","internet":"yes","science":614.76,"stu_wgt":1.8277,"desk":"yes","room":"yes","dishwasher":"yes","television":"2","computer_n":"3+","car":"3+","book":"51-100","wealth":1.84,"escs":1.3621,"reading":554.39},{"year":2000,"country":"LIE","school_id":"LIE_2000_51006","student_id":"LIE_2000_96","gender":"male","internet":"yes","science":517.53,"stu_wgt":1.8277,"desk":"yes","room":"yes","dishwasher":"yes","television":"3+","computer_n":"3+","car":"3+","book":"51-100","wealth":1.84,"escs":0.5291,"reading":535.65},{"year":2000,"country":"LIE","school_id":"LIE_2000_51006","student_id":"LIE_2000_98","gender":"female","internet":"yes","math":557.9,"science":536,"stu_wgt":1.8277,"desk":"yes","room":"yes","dishwasher":"yes","television":"2","computer_n":"1","car":"2","book":"251-500","wealth":0.34,"escs":-0.9592,"reading":586.02},{"year":2000,"country":"LIE","school_id":"LIE_2000_51006","student_id":"LIE_2000_99","gender":"male","internet":"no","math":576.19,"science":576.53,"stu_wgt":1.8277,"desk":"yes","room":"yes","dishwasher":"yes","television":"1","computer_n":"0","car":"2","book":"1-10","wealth":-0.85,"escs":-1.865,"reading":565.07},{"year":2000,"country":"LIE","school_id":"LIE_2000_51006","student_id":"LIE_2000_102","gender":"male","internet":"yes","science":612.09,"stu_wgt":1.8277,"desk":"yes","room":"yes","dishwasher":"yes","television":"1","computer_n":"1","car":"2","book":"more than 500","wealth":0.11,"escs":0.7757,"reading":608.66},{"year":2000,"country":"LIE","school_id":"LIE_2000_51006","student_id":"LIE_2000_103","gender":"male","internet":"yes","math":567.82,"science":552.24,"stu_wgt":1.8277,"desk":"yes","room":"yes","dishwasher":"yes","computer_n":"2","car":"1","book":"more than 500","wealth":0.48,"escs":1.2068,"reading":523.3},{"year":2000,"country":"LIE","school_id":"LIE_2000_51006","student_id":"LIE_2000_105","gender":"male","internet":"yes","science":543.53,"stu_wgt":1.8277,"desk":"yes","room":"yes","dishwasher":"yes","television":"3+","computer_n":"2","car":"2","book":"11-50","wealth":1.46,"escs":1.0664,"reading":584.12},{"year":2000,"country":"LIE","school_id":"LIE_2000_51006","student_id":"LIE_2000_111","gender":"female","internet":"yes","math":626.59,"science":586.52,"stu_wgt":1.8277,"desk":"yes","room":"yes","dishwasher":"yes","television":"1","computer_n":"2","car":"2","book":"251-500","wealth":0.11,"escs":1.7619,"reading":632.38},{"year":2000,"country":"LIE","school_id":"LIE_2000_51006","student_id":"LIE_2000_113","gender":"female","internet":"yes","science":622.88,"stu_wgt":1.8277,"desk":"yes","room":"yes","dishwasher":"yes","television":"3+","computer_n":"2","car":"3+","wealth":1.84,"escs":0.2355,"reading":609.84},{"year":2000,"country":"LIE","school_id":"LIE_2000_51006","student_id":"LIE_2000_118","gender":"male","internet":"yes","science":553.46,"stu_wgt":1.8277,"desk":"yes","room":"yes","dishwasher":"yes","television":"3+","computer_n":"2","car":"3+","book":"101-250","wealth":2.36,"escs":0.839,"reading":558.67},{"year":2000,"country":"LIE","school_id":"LIE_2000_51006","student_id":"LIE_2000_119","gender":"male","internet":"no","science":560.67,"stu_wgt":1.8277,"desk":"yes","room":"yes","dishwasher":"no","television":"1","computer_n":"1","car":"1","book":"101-250","wealth":-1.46,"escs":-0.442,"reading":535.95},{"year":2000,"country":"LIE","school_id":"LIE_2000_51006","student_id":"LIE_2000_120","gender":"female","internet":"yes","math":568.55,"science":509.77,"stu_wgt":1.8277,"desk":"yes","room":"no","dishwasher":"yes","television":"3+","computer_n":"2","car":"2","book":"51-100","wealth":0.52,"escs":0.708,"reading":536.89},{"year":2000,"country":"LIE","school_id":"LIE_2000_51006","student_id":"LIE_2000_121","gender":"male","internet":"no","science":520.94,"stu_wgt":1.8277,"desk":"yes","room":"yes","dishwasher":"yes","television":"3+","computer_n":"1","car":"1","book":"1-10","wealth":0.34,"escs":-0.2929,"reading":521.67},{"year":2000,"country":"LIE","school_id":"LIE_2000_51006","student_id":"LIE_2000_122","gender":"male","internet":"yes","science":626.52,"stu_wgt":1.8277,"desk":"yes","room":"yes","dishwasher":"yes","television":"3+","computer_n":"1","car":"2","book":"101-250","wealth":0.34,"escs":-0.746,"reading":559.58},{"year":2000,"country":"LIE","school_id":"LIE_2000_51006","student_id":"LIE_2000_123","gender":"female","internet":"no","science":509.25,"stu_wgt":1.8277,"desk":"yes","room":"yes","dishwasher":"yes","television":"3+","computer_n":"1","car":"2","book":"101-250","wealth":0.34,"escs":0.2135,"reading":571.39},{"year":2000,"country":"LIE","school_id":"LIE_2000_51006","student_id":"LIE_2000_124","gender":"male","internet":"no","science":675.39,"stu_wgt":1.8277,"desk":"yes","room":"yes","dishwasher":"yes","television":"3+","computer_n":"2","car":"1","book":"101-250","wealth":0.85,"escs":0.3198,"reading":664.72},{"year":2000,"country":"LIE","school_id":"LIE_2000_51006","student_id":"LIE_2000_126","gender":"male","internet":"yes","math":670.86,"science":606.36,"stu_wgt":1.8277,"desk":"yes","room":"yes","dishwasher":"yes","television":"1","computer_n":"2","car":"1","book":"more than 500","wealth":-0.12,"escs":0.2573,"reading":630.56},{"year":2000,"country":"LIE","school_id":"LIE_2000_51006","student_id":"LIE_2000_127","gender":"female","internet":"yes","science":521.88,"stu_wgt":1.8277,"desk":"yes","room":"yes","dishwasher":"yes","television":"2","computer_n":"1","car":"2","book":"251-500","wealth":-0.12,"escs":1.0835,"reading":670.47},{"year":2000,"country":"LIE","school_id":"LIE_2000_51006","student_id":"LIE_2000_128","gender":"female","internet":"no","math":589.96,"science":535.1,"stu_wgt":1.8277,"desk":"yes","room":"yes","dishwasher":"yes","television":"1","computer_n":"1","car":"2","book":"101-250","wealth":0.59,"escs":0.1005,"reading":536.94},{"year":2000,"country":"LIE","school_id":"LIE_2000_51006","student_id":"LIE_2000_129","gender":"male","internet":"yes","science":593.15,"stu_wgt":1.8277,"desk":"yes","room":"yes","dishwasher":"yes","television":"2","computer_n":"1","car":"2","book":"101-250","wealth":0.85,"escs":0.9554,"reading":595.94},{"year":2000,"country":"LIE","school_id":"LIE_2000_51006","student_id":"LIE_2000_131","gender":"female","internet":"no","math":726.54,"science":721.76,"stu_wgt":1.8277,"desk":"yes","room":"yes","dishwasher":"yes","television":"3+","computer_n":"1","car":"2","book":"251-500","wealth":0.11,"escs":-0.0104,"reading":729.58},{"year":2000,"country":"LIE","school_id":"LIE_2000_51006","student_id":"LIE_2000_132","gender":"male","internet":"yes","science":610.25,"stu_wgt":1.8277,"desk":"yes","room":"yes","dishwasher":"yes","television":"2","computer_n":"2","car":"3+","book":"251-500","wealth":1.46,"escs":1.9975,"reading":569.84},{"year":2000,"country":"LIE","school_id":"LIE_2000_51007","student_id":"LIE_2000_137","gender":"male","internet":"no","science":406.38,"stu_wgt":1.8878,"desk":"yes","room":"yes","dishwasher":"yes","television":"3+","computer_n":"1","car":"1","book":"11-50","wealth":0.11,"escs":-0.331,"reading":290.8},{"year":2000,"country":"LIE","school_id":"LIE_2000_51007","student_id":"LIE_2000_138","gender":"female","internet":"no","math":322.06,"science":290.64,"stu_wgt":1.8878,"desk":"yes","room":"yes","dishwasher":"yes","television":"2","computer_n":"0","car":"2","book":"51-100","wealth":-0.36,"reading":257.9},{"year":2000,"country":"LIE","school_id":"LIE_2000_51007","student_id":"LIE_2000_139","gender":"male","internet":"no","math":427.36,"science":503.46,"stu_wgt":1.8878,"desk":"yes","room":"yes","dishwasher":"yes","television":"3+","computer_n":"1","car":"3+","book":"11-50","wealth":0.59,"escs":-0.6096,"reading":465.99},{"year":2000,"country":"LIE","school_id":"LIE_2000_51007","student_id":"LIE_2000_143","gender":"male","internet":"yes","math":389.23,"science":335.74,"stu_wgt":1.8878,"desk":"yes","room":"yes","dishwasher":"yes","television":"3+","computer_n":"2","car":"1","book":"251-500","wealth":0.85,"escs":-0.4285,"reading":264.26},{"year":2000,"country":"LIE","school_id":"LIE_2000_51007","student_id":"LIE_2000_144","gender":"female","internet":"no","math":302.22,"science":376.34,"stu_wgt":1.8878,"desk":"yes","room":"yes","dishwasher":"no","television":"2","computer_n":"1","car":"1","book":"51-100","wealth":-0.85,"escs":-1.4573,"reading":381.51},{"year":2000,"country":"LIE","school_id":"LIE_2000_51007","student_id":"LIE_2000_145","gender":"male","science":239.54,"stu_wgt":1.8878,"dishwasher":"no","television":"1","car":"1","book":"none","wealth":-1.29,"escs":-2.8647,"reading":207.82},{"year":2000,"country":"LIE","school_id":"LIE_2000_51007","student_id":"LIE_2000_146","gender":"female","internet":"yes","math":319.01,"science":274.4,"stu_wgt":1.8878,"desk":"yes","room":"yes","dishwasher":"yes","television":"2","computer_n":"1","car":"1","book":"1-10","wealth":0.34,"escs":0.9517,"reading":268.8},{"year":2000,"country":"LIE","school_id":"LIE_2000_51007","student_id":"LIE_2000_147","gender":"female","internet":"yes","math":367.82,"science":296.89,"stu_wgt":1.8878,"desk":"yes","room":"yes","dishwasher":"yes","television":"2","computer_n":"2","car":"1","book":"101-250","wealth":0.59,"escs":0.376,"reading":296.02},{"year":2000,"country":"LIE","school_id":"LIE_2000_51007","student_id":"LIE_2000_150","gender":"male","internet":"yes","science":404.58,"stu_wgt":1.8878,"desk":"yes","room":"yes","dishwasher":"yes","television":"3+","computer_n":"2","car":"3+","book":"11-50","wealth":1.14,"escs":-0.2275,"reading":358.06},{"year":2000,"country":"LIE","school_id":"LIE_2000_51007","student_id":"LIE_2000_151","gender":"female","internet":"no","science":427.13,"stu_wgt":1.8878,"desk":"yes","room":"yes","dishwasher":"yes","television":"2","computer_n":"0","car":"1","book":"11-50","wealth":-0.36,"escs":-0.7457,"reading":472.59},{"year":2000,"country":"LIE","school_id":"LIE_2000_51007","student_id":"LIE_2000_152","gender":"male","internet":"no","science":492.98,"stu_wgt":1.8878,"desk":"no","room":"no","dishwasher":"no","television":"1","computer_n":"1","car":"1","book":"11-50","wealth":-1.46,"escs":-2.4109,"reading":446.23},{"year":2000,"country":"LIE","school_id":"LIE_2000_51007","student_id":"LIE_2000_153","gender":"female","internet":"no","science":324.48,"stu_wgt":1.8878,"desk":"yes","room":"yes","dishwasher":"no","television":"2","computer_n":"1","car":"0","book":"11-50","wealth":-0.36,"escs":-0.3498,"reading":322.96},{"year":2000,"country":"LIE","school_id":"LIE_2000_51007","student_id":"LIE_2000_154","gender":"female","internet":"no","science":415.44,"stu_wgt":1.8878,"desk":"yes","room":"no","dishwasher":"yes","television":"2","computer_n":"1","car":"2","book":"251-500","wealth":-0.12,"escs":-0.7712,"reading":406.88},{"year":2000,"country":"LIE","school_id":"LIE_2000_51007","student_id":"LIE_2000_156","gender":"male","internet":"no","science":522.94,"stu_wgt":1.8878,"desk":"yes","room":"yes","dishwasher":"yes","television":"2","computer_n":"0","car":"1","book":"51-100","wealth":-0.6,"escs":-0.6552,"reading":492.93},{"year":2000,"country":"LIE","school_id":"LIE_2000_51007","student_id":"LIE_2000_158","gender":"female","internet":"no","science":402.81,"stu_wgt":1.8878,"desk":"yes","room":"yes","dishwasher":"yes","television":"2","computer_n":"1","car":"3+","book":"11-50","wealth":0.11,"escs":-0.5981,"reading":463.23},{"year":2000,"country":"LIE","school_id":"LIE_2000_51007","student_id":"LIE_2000_159","gender":"female","internet":"no","science":415.4,"stu_wgt":1.8878,"desk":"no","room":"no","dishwasher":"yes","television":"2","computer_n":"0","car":"1","book":"11-50","wealth":-0.85,"escs":-0.7764,"reading":408.96},{"year":2000,"country":"LIE","school_id":"LIE_2000_51007","student_id":"LIE_2000_162","gender":"male","internet":"no","science":522.79,"stu_wgt":1.8878,"desk":"yes","room":"yes","dishwasher":"yes","television":"3+","computer_n":"1","book":"51-100","wealth":-0.48,"escs":-0.9591,"reading":431.42},{"year":2000,"country":"LIE","school_id":"LIE_2000_51007","student_id":"LIE_2000_166","gender":"female","internet":"no","science":512.11,"stu_wgt":1.8878,"desk":"yes","room":"yes","dishwasher":"no","television":"2","computer_n":"1","car":"2","book":"51-100","wealth":-0.12,"escs":-0.5967,"reading":492.02},{"year":2000,"country":"LIE","school_id":"LIE_2000_51007","student_id":"LIE_2000_167","gender":"female","internet":"no","math":429.65,"science":483.61,"stu_wgt":1.8878,"desk":"yes","room":"yes","dishwasher":"yes","television":"3+","computer_n":"3+","car":"2","book":"51-100","wealth":1.84,"escs":-0.1887,"reading":498.71},{"year":2000,"country":"LIE","school_id":"LIE_2000_51007","student_id":"LIE_2000_168","gender":"male","internet":"no","math":529.63,"science":403.33,"stu_wgt":1.8878,"desk":"yes","room":"no","dishwasher":"yes","television":"1","computer_n":"0","car":"1","book":"11-50","wealth":-1.84,"escs":-0.3514,"reading":414.18},{"year":2000,"country":"LIE","school_id":"LIE_2000_51007","student_id":"LIE_2000_170","gender":"male","internet":"no","science":202.55,"stu_wgt":1.8878,"desk":"yes","room":"yes","dishwasher":"yes","television":"2","computer_n":"1","car":"3+","book":"11-50","wealth":0.85,"escs":-0.7872,"reading":180.55},{"year":2000,"country":"LIE","school_id":"LIE_2000_51007","student_id":"LIE_2000_171","gender":"female","internet":"no","science":482.35,"stu_wgt":1.8878,"desk":"yes","room":"yes","dishwasher":"no","television":"3+","computer_n":"0","car":"1","book":"11-50","wealth":-0.36,"escs":-0.787,"reading":468.39},{"year":2000,"country":"LIE","school_id":"LIE_2000_51007","student_id":"LIE_2000_172","gender":"male","internet":"no","science":300.13,"stu_wgt":1.8878,"desk":"yes","room":"yes","dishwasher":"no","television":"1","computer_n":"0","car":"1","book":"11-50","wealth":-1.46,"escs":-0.1691,"reading":294.78},{"year":2000,"country":"LIE","school_id":"LIE_2000_51007","student_id":"LIE_2000_173","gender":"female","internet":"no","math":346.45,"science":440.31,"stu_wgt":1.8878,"desk":"yes","room":"yes","dishwasher":"yes","television":"3+","computer_n":"1","car":"2","book":"11-50","wealth":0.59,"escs":-0.3462,"reading":378.73},{"year":2000,"country":"LIE","school_id":"LIE_2000_51008","student_id":"LIE_2000_175","gender":"male","internet":"no","math":442.65,"science":378.14,"stu_wgt":1.8,"desk":"yes","room":"yes","dishwasher":"yes","television":"2","computer_n":"1","car":"2","book":"51-100","wealth":-0.12,"escs":-0.6628,"reading":351.52},{"year":2000,"country":"LIE","school_id":"LIE_2000_51008","student_id":"LIE_2000_177","gender":"male","internet":"yes","science":625.78,"stu_wgt":1.8,"desk":"yes","room":"yes","dishwasher":"yes","television":"3+","computer_n":"1","car":"1","book":"101-250","wealth":0.85,"escs":0.3735,"reading":616.55},{"year":2000,"country":"LIE","school_id":"LIE_2000_51008","student_id":"LIE_2000_178","gender":"male","internet":"no","math":573.16,"science":547.73,"stu_wgt":1.8,"desk":"yes","room":"yes","dishwasher":"no","television":"1","computer_n":"1","car":"2","book":"11-50","wealth":-0.36,"escs":-0.2651,"reading":512.4},{"year":2000,"country":"LIE","school_id":"LIE_2000_51008","student_id":"LIE_2000_179","gender":"female","internet":"no","science":482.15,"stu_wgt":1.8,"desk":"yes","room":"yes","dishwasher":"yes","television":"1","computer_n":"1","car":"3+","book":"101-250","wealth":0.11,"escs":1.2732,"reading":451.68},{"year":2000,"country":"LIE","school_id":"LIE_2000_51008","student_id":"LIE_2000_181","gender":"female","internet":"no","science":393.75,"stu_wgt":1.8,"desk":"yes","room":"yes","dishwasher":"yes","television":"1","computer_n":"1","car":"3+","book":"251-500","wealth":-0.36,"escs":-0.4469,"reading":416.23},{"year":2000,"country":"LIE","school_id":"LIE_2000_51008","student_id":"LIE_2000_182","gender":"male","internet":"no","science":594.95,"stu_wgt":1.8,"desk":"no","room":"yes","dishwasher":"no","television":"1","computer_n":"1","car":"2","book":"101-250","wealth":-0.6,"escs":-0.8693,"reading":535.04},{"year":2000,"country":"LIE","school_id":"LIE_2000_51008","student_id":"LIE_2000_184","gender":"female","internet":"yes","science":399.2,"stu_wgt":1.8,"desk":"yes","room":"yes","dishwasher":"yes","television":"3+","computer_n":"1","car":"1","book":"11-50","wealth":0.11,"escs":-0.638,"reading":492.32},{"year":2000,"country":"LIE","school_id":"LIE_2000_51008","student_id":"LIE_2000_185","gender":"male","internet":"no","math":645.64,"science":510.68,"stu_wgt":1.8,"desk":"yes","room":"yes","dishwasher":"no","television":"3+","computer_n":"2","car":"2","book":"101-250","wealth":0.34,"escs":-0.5444,"reading":491.44},{"year":2000,"country":"LIE","school_id":"LIE_2000_51008","student_id":"LIE_2000_186","gender":"male","internet":"no","math":567.03,"science":544.95,"stu_wgt":1.8,"desk":"yes","room":"yes","dishwasher":"yes","television":"1","computer_n":"1","car":"1","book":"101-250","wealth":-0.36,"escs":-1.207,"reading":525.98},{"year":2000,"country":"LIE","school_id":"LIE_2000_51008","student_id":"LIE_2000_187","gender":"female","internet":"no","math":454.83,"science":465.57,"stu_wgt":1.8,"desk":"yes","room":"yes","dishwasher":"yes","television":"3+","computer_n":"2","car":"2","book":"101-250","wealth":0.85,"escs":0.6575,"reading":417.82},{"year":2000,"country":"LIE","school_id":"LIE_2000_51008","student_id":"LIE_2000_189","gender":"female","internet":"yes","science":503.09,"stu_wgt":1.8,"desk":"yes","room":"yes","dishwasher":"yes","television":"2","computer_n":"1","car":"2","book":"101-250","wealth":0.8,"escs":0.8275,"reading":592.91},{"year":2000,"country":"LIE","school_id":"LIE_2000_51008","student_id":"LIE_2000_191","gender":"male","internet":"no","math":551.79,"science":507.14,"stu_wgt":1.8,"desk":"yes","room":"yes","dishwasher":"yes","television":"1","computer_n":"1","car":"1","book":"251-500","wealth":-0.85,"escs":0.3544,"reading":507.85},{"year":2000,"country":"LIE","school_id":"LIE_2000_51009","student_id":"LIE_2000_196","gender":"female","internet":"yes","math":416.67,"science":398.82,"stu_wgt":1.8,"desk":"yes","room":"yes","dishwasher":"yes","television":"3+","computer_n":"2","car":"1","book":"11-50","wealth":0.59,"escs":0.1633,"reading":411.46},{"year":2000,"country":"LIE","school_id":"LIE_2000_51009","student_id":"LIE_2000_198","gender":"male","internet":"no","science":459.6,"stu_wgt":1.8,"desk":"yes","room":"yes","dishwasher":"no","television":"3+","computer_n":"1","car":"1","book":"11-50","wealth":0.11,"escs":-0.5347,"reading":463.5},{"year":2000,"country":"LIE","school_id":"LIE_2000_51009","student_id":"LIE_2000_201","gender":"female","internet":"no","science":303.74,"stu_wgt":1.8,"desk":"yes","room":"yes","dishwasher":"yes","television":"3+","computer_n":"1","car":"1","book":"251-500","wealth":0.59,"escs":0.6575,"reading":372.04},{"year":2000,"country":"LIE","school_id":"LIE_2000_51009","student_id":"LIE_2000_203","gender":"male","internet":"yes","math":526.58,"science":394.31,"stu_wgt":1.8,"desk":"yes","room":"yes","dishwasher":"yes","television":"2","computer_n":"1","car":"1","book":"11-50","wealth":0.11,"escs":-0.2783,"reading":451.45},{"year":2000,"country":"LIE","school_id":"LIE_2000_51009","student_id":"LIE_2000_204","gender":"male","internet":"yes","math":575.45,"science":492.7,"stu_wgt":1.8,"desk":"yes","room":"yes","dishwasher":"yes","television":"3+","computer_n":"1","car":"2","book":"51-100","wealth":0.59,"escs":-0.478,"reading":514.22},{"year":2000,"country":"LIE","school_id":"LIE_2000_51009","student_id":"LIE_2000_205","gender":"male","internet":"no","math":290.74,"science":177.81,"stu_wgt":1.8,"desk":"yes","room":"yes","dishwasher":"no","television":"3+","computer_n":"3+","car":"3+","book":"11-50","wealth":1.46,"escs":0.8322,"reading":143.32},{"year":2000,"country":"LIE","school_id":"LIE_2000_51009","student_id":"LIE_2000_208","gender":"male","internet":"no","science":340.57,"stu_wgt":1.8,"desk":"yes","room":"yes","dishwasher":"yes","television":"2","computer_n":"3+","car":"1","book":"11-50","wealth":0.59,"escs":-0.7456,"reading":361.43},{"year":2000,"country":"LIE","school_id":"LIE_2000_51009","student_id":"LIE_2000_209","gender":"female","internet":"no","science":260.28,"stu_wgt":1.8,"desk":"yes","room":"yes","dishwasher":"no","television":"2","computer_n":"1","car":"1","book":"51-100","wealth":-1.13,"escs":-1.6334,"reading":300.53},{"year":2000,"country":"LIE","school_id":"LIE_2000_51009","student_id":"LIE_2000_213","gender":"female","internet":"yes","science":325.19,"stu_wgt":1.8,"desk":"yes","room":"yes","dishwasher":"yes","television":"2","computer_n":"1","car":"3+","book":"101-250","wealth":0.59,"escs":0.3738,"reading":362.61},{"year":2000,"country":"LIE","school_id":"LIE_2000_51009","student_id":"LIE_2000_214","gender":"male","internet":"no","science":368.49,"stu_wgt":1.8,"desk":"no","room":"no","dishwasher":"no","television":"1","computer_n":"1","car":"1","book":"1-10","wealth":-1.84,"escs":-1.7299,"reading":284.44},{"year":2000,"country":"LIE","school_id":"LIE_2000_51009","student_id":"LIE_2000_217","gender":"male","internet":"yes","math":389.23,"science":417.83,"stu_wgt":1.8,"desk":"yes","room":"yes","dishwasher":"yes","television":"2","computer_n":"2","car":"2","book":"11-50","wealth":0.85,"escs":0.8824,"reading":333.34},{"year":2000,"country":"LIE","school_id":"LIE_2000_51009","student_id":"LIE_2000_218","gender":"female","internet":"yes","science":468.82,"stu_wgt":1.8,"desk":"yes","room":"yes","dishwasher":"yes","television":"3+","computer_n":"1","car":"2","book":"101-250","wealth":0.11,"escs":1.2555,"reading":502.02},{"year":2000,"country":"LIE","school_id":"LIE_2000_51009","student_id":"LIE_2000_221","gender":"male","internet":"no","science":494.78,"stu_wgt":1.8,"desk":"yes","room":"yes","dishwasher":"no","television":"3+","computer_n":"1","car":"1","book":"51-100","wealth":-0.6,"escs":-0.8669,"reading":458.04},{"year":2000,"country":"LIE","school_id":"LIE_2000_51009","student_id":"LIE_2000_222","gender":"female","internet":"no","science":404.77,"stu_wgt":1.8,"desk":"yes","room":"yes","dishwasher":"no","television":"1","computer_n":"3+","car":"2","book":"101-250","wealth":0.11,"escs":-0.9979,"reading":369.32},{"year":2000,"country":"LIE","school_id":"LIE_2000_51009","student_id":"LIE_2000_223","gender":"female","internet":"no","math":394.54,"science":421.37,"stu_wgt":1.8,"desk":"yes","room":"yes","dishwasher":"yes","television":"2","computer_n":"1","car":"1","book":"11-50","wealth":-0.12,"escs":-0.4247,"reading":428.73},{"year":2000,"country":"LIE","school_id":"LIE_2000_51009","student_id":"LIE_2000_224","gender":"male","internet":"yes","science":423.56,"stu_wgt":1.8,"desk":"yes","room":"yes","dishwasher":"yes","television":"3+","computer_n":"1","car":"2","book":"251-500","wealth":0.85,"escs":0.8146,"reading":435.96},{"year":2000,"country":"LIE","school_id":"LIE_2000_51009","student_id":"LIE_2000_226","gender":"female","internet":"no","math":370.11,"science":330.26,"stu_wgt":1.8,"desk":"yes","room":"yes","dishwasher":"yes","television":"3+","computer_n":"0","car":"1","book":"101-250","wealth":-0.6,"escs":-0.589,"reading":433.27},{"year":2000,"country":"LIE","school_id":"LIE_2000_51009","student_id":"LIE_2000_227","gender":"female","internet":"yes","science":417.4,"stu_wgt":1.8,"desk":"yes","room":"yes","dishwasher":"yes","television":"3+","computer_n":"1","car":"2","book":"101-250","wealth":1.46,"escs":0.1414,"reading":435.67},{"year":2000,"country":"LIE","school_id":"LIE_2000_51009","student_id":"LIE_2000_230","internet":"no","math":377.01,"science":352.88,"stu_wgt":1.8,"desk":"no","room":"yes","dishwasher":"yes","television":"3+","computer_n":"1","car":"2","book":"1-10","wealth":0.11,"escs":-1.3079,"reading":366.06},{"year":2000,"country":"LIE","school_id":"LIE_2000_51009","student_id":"LIE_2000_233","gender":"male","internet":"yes","science":420.85,"stu_wgt":1.8,"desk":"yes","room":"yes","dishwasher":"yes","television":"3+","computer_n":"2","car":"3+","book":"51-100","wealth":1.84,"escs":0.1069,"reading":358.7},{"year":2000,"country":"LIE","school_id":"LIE_2000_51009","student_id":"LIE_2000_234","gender":"female","internet":"no","science":344.18,"stu_wgt":1.8,"desk":"yes","room":"yes","dishwasher":"no","television":"2","computer_n":"0","car":"2","book":"51-100","wealth":-0.85,"escs":-0.2967,"reading":385.06},{"year":2000,"country":"LIE","school_id":"LIE_2000_51009","student_id":"LIE_2000_235","gender":"female","internet":"no","math":330.46,"science":443.99,"stu_wgt":1.8,"desk":"yes","room":"yes","dishwasher":"no","television":"2","computer_n":"1","car":"2","book":"1-10","wealth":-0.36,"escs":-1.207,"reading":402.42},{"year":2000,"country":"LIE","school_id":"LIE_2000_51009","student_id":"LIE_2000_236","gender":"female","internet":"no","science":534.67,"stu_wgt":1.8,"desk":"yes","room":"yes","dishwasher":"yes","television":"3+","computer_n":"1","car":"2","book":"51-100","wealth":0.34,"escs":-0.5002,"reading":476.57},{"year":2000,"country":"LIE","school_id":"LIE_2000_51009","student_id":"LIE_2000_238","gender":"male","internet":"no","math":414.41,"science":472.86,"stu_wgt":1.8,"desk":"yes","room":"yes","dishwasher":"no","television":"2","computer_n":"0","car":"0","book":"1-10","wealth":-1.46,"escs":-1.0881,"reading":404.23},{"year":2000,"country":"LIE","school_id":"LIE_2000_51010","student_id":"LIE_2000_239","gender":"male","internet":"yes","science":429.87,"stu_wgt":1.8383,"desk":"yes","room":"yes","dishwasher":"yes","television":"2","computer_n":"1","car":"1","book":"11-50","wealth":-0.12,"escs":-0.1984,"reading":437.78},{"year":2000,"country":"LIE","school_id":"LIE_2000_51010","student_id":"LIE_2000_240","gender":"female","internet":"no","math":505.97,"science":486.32,"stu_wgt":1.8383,"desk":"yes","room":"yes","dishwasher":"yes","television":"2","computer_n":"1","car":"2","book":"251-500","wealth":0.11,"escs":1.1666,"reading":431.45},{"year":2000,"country":"LIE","school_id":"LIE_2000_51010","student_id":"LIE_2000_241","gender":"female","internet":"no","science":581.57,"stu_wgt":1.8383,"desk":"yes","room":"yes","dishwasher":"yes","television":"2","computer_n":"1","car":"2","book":"51-100","wealth":0.34,"escs":-0.3035,"reading":594.73},{"year":2000,"country":"LIE","school_id":"LIE_2000_51010","student_id":"LIE_2000_242","gender":"female","internet":"no","science":511.96,"stu_wgt":1.8383,"desk":"no","room":"no","dishwasher":"yes","television":"3+","computer_n":"2","car":"3+","book":"51-100","wealth":0.85,"escs":-0.1419,"reading":600.48},{"year":2000,"country":"LIE","school_id":"LIE_2000_51010","student_id":"LIE_2000_244","gender":"female","internet":"no","science":547.3,"stu_wgt":1.8383,"desk":"yes","room":"yes","dishwasher":"yes","television":"0","computer_n":"0","car":"2","book":"51-100","wealth":-1.13,"escs":-0.7697,"reading":575.64},{"year":2000,"country":"LIE","school_id":"LIE_2000_51010","student_id":"LIE_2000_245","gender":"male","internet":"yes","science":490.27,"stu_wgt":1.8383,"desk":"yes","room":"yes","dishwasher":"yes","television":"3+","computer_n":"2","car":"1","book":"11-50","wealth":1.14,"escs":-0.1887,"reading":415.32},{"year":2000,"country":"LIE","school_id":"LIE_2000_51010","student_id":"LIE_2000_247","gender":"female","internet":"yes","math":506.73,"science":497.15,"stu_wgt":1.8383,"desk":"yes","room":"yes","dishwasher":"yes","television":"3+","computer_n":"2","car":"1","book":"51-100","wealth":0.59,"escs":-0.5182,"reading":565.98},{"year":2000,"country":"LIE","school_id":"LIE_2000_51010","student_id":"LIE_2000_249","gender":"female","internet":"no","math":563.24,"science":451.21,"stu_wgt":1.8383,"desk":"yes","room":"yes","dishwasher":"yes","television":"3+","computer_n":"0","car":"1","book":"11-50","wealth":-0.12,"escs":-1.2243,"reading":457.86},{"year":2000,"country":"LIE","school_id":"LIE_2000_51010","student_id":"LIE_2000_250","gender":"female","internet":"yes","science":370.34,"stu_wgt":1.8383,"desk":"yes","room":"yes","dishwasher":"yes","television":"2","computer_n":"2","car":"2","book":"101-250","wealth":0.85,"escs":-0.0886,"reading":465.05},{"year":2000,"country":"LIE","school_id":"LIE_2000_51010","student_id":"LIE_2000_252","gender":"female","internet":"no","math":481.58,"science":362.8,"stu_wgt":1.8383,"desk":"yes","room":"yes","dishwasher":"yes","television":"3+","computer_n":"2","car":"3+","book":"11-50","wealth":0.85,"escs":-1.1306,"reading":396.96},{"year":2000,"country":"LIE","school_id":"LIE_2000_51010","student_id":"LIE_2000_253","gender":"female","internet":"yes","science":511.92,"stu_wgt":1.8383,"desk":"yes","room":"yes","dishwasher":"yes","television":"1","computer_n":"1","car":"1","book":"51-100","wealth":-0.6,"escs":0.7292,"reading":566.21},{"year":2000,"country":"LIE","school_id":"LIE_2000_51010","student_id":"LIE_2000_256","gender":"male","internet":"yes","math":627.32,"science":404.23,"stu_wgt":1.8383,"desk":"yes","room":"yes","dishwasher":"yes","television":"2","computer_n":"2","car":"2","book":"51-100","wealth":0.85,"escs":0.4684,"reading":464.17},{"year":2000,"country":"LIE","school_id":"LIE_2000_51010","student_id":"LIE_2000_259","gender":"male","internet":"yes","math":530.39,"science":530.52,"stu_wgt":1.8383,"desk":"yes","room":"yes","dishwasher":"yes","television":"1","computer_n":"2","car":"3+","book":"11-50","wealth":0.85,"escs":0.8824,"reading":522.35},{"year":2000,"country":"LIE","school_id":"LIE_2000_51010","student_id":"LIE_2000_261","gender":"female","internet":"no","science":593.11,"stu_wgt":1.8383,"desk":"yes","room":"yes","dishwasher":"yes","television":"2","computer_n":"2","car":"2","book":"more than 500","wealth":0.59,"escs":1.0811,"reading":629.83},{"year":2000,"country":"LIE","school_id":"LIE_2000_51010","student_id":"LIE_2000_264","gender":"female","internet":"no","math":486.92,"science":476.47,"stu_wgt":1.8383,"desk":"yes","room":"yes","dishwasher":"yes","television":"3+","computer_n":"0","car":"2","book":"more than 500","wealth":-0.12,"escs":0.8824,"reading":478.77},{"year":2000,"country":"LIE","school_id":"LIE_2000_51010","student_id":"LIE_2000_265","gender":"male","internet":"no","science":476.03,"stu_wgt":1.8383,"desk":"yes","room":"yes","dishwasher":"yes","television":"2","computer_n":"2","car":"2","book":"101-250","wealth":0.34,"escs":-1.1426,"reading":509.29},{"year":2000,"country":"LIE","school_id":"LIE_2000_51010","student_id":"LIE_2000_268","gender":"female","internet":"no","science":569.85,"stu_wgt":1.8383,"desk":"yes","room":"yes","dishwasher":"yes","television":"1","computer_n":"1","car":"2","book":"11-50","wealth":0.11,"escs":-0.3035,"reading":618.36},{"year":2000,"country":"LIE","school_id":"LIE_2000_51010","student_id":"LIE_2000_269","gender":"male","internet":"yes","math":566.26,"science":468.28,"stu_wgt":1.8383,"desk":"yes","room":"yes","dishwasher":"yes","television":"2","computer_n":"1","car":"3+","book":"51-100","wealth":1.14,"escs":1.0278,"reading":480.54},{"year":2000,"country":"LIE","school_id":"LIE_2000_51010","student_id":"LIE_2000_271","gender":"female","internet":"no","science":506.55,"stu_wgt":1.8383,"desk":"yes","room":"yes","dishwasher":"yes","television":"2","computer_n":"0","car":"3+","book":"251-500","wealth":0.34,"escs":-0.1831,"reading":475.96},{"year":2000,"country":"LIE","school_id":"LIE_2000_51010","student_id":"LIE_2000_274","gender":"female","internet":"yes","math":470.89,"science":543.22,"stu_wgt":1.8383,"desk":"yes","room":"yes","dishwasher":"yes","television":"3+","computer_n":"0","car":"1","book":"251-500","wealth":0.59,"escs":0.2385,"reading":556.94},{"year":2000,"country":"LIE","school_id":"LIE_2000_51010","student_id":"LIE_2000_275","gender":"female","internet":"no","math":556.34,"science":535.03,"stu_wgt":1.8383,"desk":"yes","room":"yes","dishwasher":"yes","television":"1","computer_n":"1","car":"1","book":"11-50","wealth":-1.13,"escs":0.5389,"reading":548.71},{"year":2000,"country":"LIE","school_id":"LIE_2000_51010","student_id":"LIE_2000_276","gender":"female","internet":"no","science":538.08,"stu_wgt":1.8383,"desk":"yes","room":"yes","dishwasher":"yes","television":"1","computer_n":"1","car":"3+","book":"51-100","wealth":-0.12,"escs":-0.6335,"reading":610.75},{"year":2000,"country":"LIE","school_id":"LIE_2000_51010","student_id":"LIE_2000_279","gender":"male","internet":"yes","math":674.67,"science":542.32,"stu_wgt":1.8383,"desk":"yes","room":"yes","dishwasher":"no","television":"1","computer_n":"2","car":"1","book":"251-500","wealth":-0.12,"escs":-0.2444,"reading":592.38},{"year":2000,"country":"LIE","school_id":"LIE_2000_51010","student_id":"LIE_2000_280","gender":"female","internet":"yes","science":494.82,"stu_wgt":1.8383,"desk":"yes","room":"yes","dishwasher":"yes","television":"1","computer_n":"1","car":"1","book":"51-100","wealth":-0.6,"escs":-0.787,"reading":504.13},{"year":2000,"country":"LIE","school_id":"LIE_2000_51010","student_id":"LIE_2000_282","gender":"female","internet":"yes","math":541.87,"science":429.56,"stu_wgt":1.8383,"desk":"yes","room":"yes","dishwasher":"yes","television":"2","computer_n":"1","car":"3+","book":"101-250","wealth":0.85,"escs":-0.053,"reading":453.32},{"year":2000,"country":"LIE","school_id":"LIE_2000_51010","student_id":"LIE_2000_283","gender":"female","internet":"yes","science":657.16,"stu_wgt":1.8383,"desk":"yes","room":"yes","dishwasher":"yes","television":"3+","computer_n":"1","car":"2","book":"more than 500","wealth":0.34,"escs":1.4543,"reading":625.29},{"year":2000,"country":"LIE","school_id":"LIE_2000_51010","student_id":"LIE_2000_285","gender":"female","internet":"no","science":344.33,"stu_wgt":1.8383,"desk":"yes","room":"yes","dishwasher":"yes","television":"2","computer_n":"0","car":"2","book":"101-250","wealth":-0.12,"escs":-0.5655,"reading":402.95},{"year":2000,"country":"LIE","school_id":"LIE_2000_51011","student_id":"LIE_2000_286","gender":"male","internet":"no","science":535.38,"stu_wgt":2.025,"desk":"yes","room":"no","dishwasher":"yes","television":"1","computer_n":"0","car":"2","book":"51-100","wealth":-0.85,"escs":-0.0139,"reading":539.85},{"year":2000,"country":"LIE","school_id":"LIE_2000_51011","student_id":"LIE_2000_290","gender":"male","internet":"yes","math":547.18,"science":442.12,"stu_wgt":2.025,"desk":"yes","room":"yes","dishwasher":"yes","television":"2","computer_n":"1","car":"2","book":"251-500","wealth":0.59,"escs":0.1852,"reading":432.36},{"year":2000,"country":"LIE","school_id":"LIE_2000_51011","student_id":"LIE_2000_292","gender":"male","internet":"no","math":476.97,"science":400.62,"stu_wgt":2.025,"desk":"yes","room":"yes","dishwasher":"yes","television":"0","computer_n":"3+","car":"3+","book":"101-250","wealth":0.11,"escs":-0.0578,"reading":335.11},{"year":2000,"country":"LIE","school_id":"LIE_2000_51011","student_id":"LIE_2000_293","gender":"female","internet":"no","science":540.98,"stu_wgt":2.025,"desk":"yes","room":"yes","dishwasher":"yes","television":"2","computer_n":"1","car":"1","book":"101-250","wealth":-0.12,"escs":0.5564,"reading":552.92},{"year":2000,"country":"LIE","school_id":"LIE_2000_51011","student_id":"LIE_2000_296","gender":"male","internet":"yes","science":454.23,"stu_wgt":2.025,"desk":"yes","room":"yes","dishwasher":"yes","television":"3+","computer_n":"2","car":"1","book":"11-50","wealth":0.59,"escs":-0.0651,"reading":481.41},{"year":2000,"country":"LIE","school_id":"LIE_2000_51011","student_id":"LIE_2000_297","gender":"male","internet":"yes","science":478.74,"stu_wgt":2.025,"desk":"yes","room":"yes","dishwasher":"yes","television":"3+","computer_n":"3+","car":"2","book":"251-500","wealth":2.36,"escs":-0.0719,"reading":471.12},{"year":2000,"country":"LIE","school_id":"LIE_2000_51011","student_id":"LIE_2000_299","gender":"female","internet":"yes","science":533.61,"stu_wgt":2.025,"desk":"yes","room":"yes","dishwasher":"yes","television":"1","computer_n":"2","car":"2","book":"101-250","wealth":0.59,"escs":1.0835,"reading":589.57},{"year":2000,"country":"LIE","school_id":"LIE_2000_51011","student_id":"LIE_2000_300","gender":"female","internet":"yes","math":589.19,"science":466.54,"stu_wgt":2.025,"desk":"yes","room":"yes","dishwasher":"yes","television":"3+","computer_n":"2","car":"2","book":"251-500","wealth":1.14,"escs":0.1293,"reading":553.3},{"year":2000,"country":"LIE","school_id":"LIE_2000_51011","student_id":"LIE_2000_301","gender":"male","internet":"no","math":523.55,"science":375.43,"stu_wgt":2.025,"desk":"no","room":"no","dishwasher":"no","book":"more than 500","wealth":-2.84,"escs":-3.7609,"reading":377.87},{"year":2000,"country":"LIE","school_id":"LIE_2000_52001","student_id":"LIE_2000_303","gender":"male","internet":"yes","math":555.61,"science":563.06,"stu_wgt":1.9384,"desk":"yes","room":"yes","dishwasher":"no","television":"1","computer_n":"1","car":"1","book":"more than 500","wealth":-0.6,"escs":0.9295,"reading":546.94},{"year":2000,"country":"LIE","school_id":"LIE_2000_52001","student_id":"LIE_2000_304","gender":"female","internet":"no","science":433.44,"stu_wgt":1.9384,"desk":"yes","room":"yes","dishwasher":"yes","television":"2","computer_n":"1","car":"3+","book":"101-250","wealth":0.59,"escs":0.7402,"reading":448.05},{"year":2000,"country":"LIE","school_id":"LIE_2000_52001","student_id":"LIE_2000_305","gender":"male","internet":"yes","science":375.75,"stu_wgt":1.9384,"desk":"yes","room":"yes","dishwasher":"yes","television":"3+","computer_n":"1","car":"2","book":"51-100","wealth":1.14,"escs":0.8604,"reading":392.33},{"year":2000,"country":"LIE","school_id":"LIE_2000_52001","student_id":"LIE_2000_306","gender":"male","internet":"no","science":364.88,"stu_wgt":1.9384,"desk":"yes","room":"yes","dishwasher":"yes","television":"1","computer_n":"3+","car":"3+","book":"1-10","wealth":0.39,"escs":0.5455,"reading":300.8},{"year":2000,"country":"LIE","school_id":"LIE_2000_52001","student_id":"LIE_2000_308","gender":"male","internet":"yes","math":493.76,"science":452.94,"stu_wgt":1.9384,"desk":"yes","room":"yes","dishwasher":"yes","television":"2","computer_n":"2","car":"1","book":"51-100","wealth":0.11,"escs":0.2166,"reading":417.82},{"year":2000,"country":"LIE","school_id":"LIE_2000_52001","student_id":"LIE_2000_310","gender":"male","internet":"yes","science":562.63,"stu_wgt":1.9384,"desk":"yes","room":"yes","dishwasher":"yes","television":"1","computer_n":"1","car":"2","book":"101-250","wealth":0.11,"escs":0.7935,"reading":503.84},{"year":2000,"country":"LIE","school_id":"LIE_2000_52002","student_id":"LIE_2000_311","gender":"male","internet":"yes","math":507.53,"science":584.71,"stu_wgt":1.9384,"desk":"yes","room":"yes","dishwasher":"yes","television":"0","computer_n":"2","car":"1","book":"251-500","wealth":-0.85,"escs":0.5786,"reading":523.3},{"year":2000,"country":"LIE","school_id":"LIE_2000_52002","student_id":"LIE_2000_312","gender":"male","internet":"yes","science":499.33,"stu_wgt":1.9384,"desk":"yes","room":"yes","dishwasher":"yes","television":"1","computer_n":"1","car":"2","book":"251-500","wealth":-0.12,"escs":1.1666,"reading":485.95}]}
